Workbook

Sheet Attractions
A1: id | B1: name | C1: district | D1: coordinates | E1: category | F1: vibes | G1: environmental_tags | H1: demographic_tags | I1: summary_desc | J1: facilities_desc | K1: tips_desc
A2: acwd001 | B2: Kennedy Town New Praya | C2: =IF($A2<>"", _xlfn.IFNA(VLOOKUP(RIGHT(LEFT($A2,4),3),'District LookUp Table'!$A$2:$B$19,2,FALSE), "NOT FOUND"), "") -> Central & Western | D2: 22.283587, 114.125840 | E2: Nature & Scenary | F2: Local Favorites | G2: Outdoor | H2: Tourist Friendly | I2: Kennedy Town New Praya is a charming neighborhood blending vintage architecture with modern amenities, offering a balance of history and contemporary life. It’s a popular spot for locals and tourists alike, providing a relaxed atmosphere with waterfront views and diverse dining options. | J2: The location offers MTR access via the Kennedy Town station. A short walk leads to the Kennedy Town basketball court, offering a vantage point for observing the harbor. There is a %Arabica coffee shop with a grand view to the harbor. The area is also known for its local eateries and hip coffee shops. Walking along the waterfront is a popular activity. | K2: For a truly local experience, explore the Kennedy Town area. Enjoy the diverse dining options and the waterfront views. Be mindful of the area during peak hours to avoid crowds.
A3: acwd002 | B3: Sai Wan Swimming Shed | C3: =IF($A3<>"", _xlfn.IFNA(VLOOKUP(RIGHT(LEFT($A3,4),3),'District LookUp Table'!$A$2:$B$19,2,FALSE), "NOT FOUND"), "") -> Central & Western | D3: 22.2798456, 114.1175181 | E3: Nature & Scenery | F3: Chill, Insta-Worthy | G3: Outdoor | H3: Tourist Friendly, Couples | I3: A beautiful lookout for sunset views, offering stunning coastal scenery and a chance to capture iconic views. | J3: The location offers a wooden pier for walking and exploring. There are two staircases leading down to the pier, guiding you directly to the pier. | K3: Enjoy the sunset from the wooden pier. Take the stairs down to the pier for a unique experience. Be aware that the location can be popular, so expect a short wait for photos.
A4: acwd003 | B4: Sunset Seaview Pavillion | C4: =IF($A4<>"", _xlfn.IFNA(VLOOKUP(RIGHT(LEFT($A4,4),3),'District LookUp Table'!$A$2:$B$19,2,FALSE), "NOT FOUND"), "") -> Central & Western | D4: 22.2741043, 114.1171927 | E4: Nature & Scenery | F4: Chill | G4: Outdoor, Scenic | H4: Tourist Friendly | I4: Hong Kong offers a tranquil spot to witness stunning sunsets, particularly in a secluded area with limited crowds. A short walk down a staircase leads to a pavilion offering unobstructed views. Nearby, a large boat passage can be observed. | J4: The location offers a scenic view and is easily accessible via a 5B bus station. A short walk down the stairs leads to a viewpoint. There are multiple levels of stairs, with the UChicago campus accessible via a short walk. | K4: Be mindful of snakes roaming around the area, particularly on the path down to the pavilion. Wear protective gear against insects. The stairs can be slippery, so exercise caution.
A5: acwd004 | B5: Hong Kong Observation Wheel | C5: =IF($A5<>"", _xlfn.IFNA(VLOOKUP(RIGHT(LEFT($A5,4),3),'District LookUp Table'!$A$2:$B$19,2,FALSE), "NOT FOUND"), "") -> Central & Western | D5: 22.285354, 114.161736 | E5: Recreation & Activities | F5: Local Favorites, Insta-Worthy | G5: Budget | H5: Tourist Friendly, Couples, Family Friendly, Elderly Friendly, Pet Friendly | I5: The Hong Kong Observation Wheel is a lovely spot to enjoy the skyline, both day and night. The location is perfect — right by Victoria Harbour — offering panoramic views of Hong Kong Island, Kowloon, and the surrounding lights. | J5: The ride is smooth and lasts around 15 minutes, giving you enough time to enjoy the scenery and take photos. The cabins are air-conditioned and comfortable, making it pleasant even on warm days. Staff are friendly and the ticket price is reasonable compared to the experience. It’s great for families, couples, or anyone who loves city views. | K5: If you're in Hong Kong, even just for a few hours, this is a fun and easy way to take in the city from above. Definitely recommend i!t
A6: acwd005 | B6: Barker Road Viewing Point | C6: =IF($A6<>"", _xlfn.IFNA(VLOOKUP(RIGHT(LEFT($A6,4),3),'District LookUp Table'!$A$2:$B$19,2,FALSE), "NOT FOUND"), "") -> Central & Western | D6: 22.271291, 114.157525 | E6: Nature & Scenery | F6: Insta-Worthy, Hidden | G6: Outdoor | H6: Tourist Friendly, Solo Travelers | I6: Barker Road Viewing Point offers breathtaking panoramic views of Victoria Harbour, particularly popular with cyclists and motorcyclists. The location is a vibrant spot for capturing scenic moments and connecting with fellow enthusiasts. While traffic can occasionally disrupt the tranquility, the overall atmosphere is excellent. | J6: The viewing point offers direct access to the Victoria Harbor view. There is a roadside photo opportunity with a magnificent harbor view. A short cycling route is available from Admiralty to the Peak, offering less traffic and a more peaceful experience. The area is accessible by bicycle and offers a scenic route through the quick road. | K6: For optimal views, arrive early in the morning or late in the afternoon to avoid peak traffic. Bring a camera to capture the stunning scenery. Consider cycling to the Peak for a quieter experience.
A7: acwd006 | B7: Hong Kong Museum of Medical Sciences | C7: =IF($A7<>"", _xlfn.IFNA(VLOOKUP(RIGHT(LEFT($A7,4),3),'District LookUp Table'!$A$2:$B$19,2,FALSE), "NOT FOUND"), "") -> Central & Western | D7: 22.283415, 114.148558 | E7: Heritage & Culture | F7: Local Favorites | G7: Indoor | H7: Tourist Friendly, Family Friendly | I7: The Hong Kong Museum of Medical Sciences is a historical museum showcasing the evolution of medical science in Hong Kong, from the 19th century to the present day. It offers a comprehensive look at the history of medical practices, equipment, and research, including exhibits on the history of the plague, early medical techniques, and the development of Chinese medicine. The museum’s location in the Mid Levels of Hong Kong provides a unique setting, blending Western and traditional architectural elements. | J7: The museum features a large exhibition hall with interactive exhibits, including a simulated surgery experience, a display of medical equipment, and a presentation on the history of the plague. There is also a dedicated area for Chinese medicine exhibits, including a 3D Acu-Man exhibition. | K7: To get the best experience, take the MTR to Sheung Wan or Sai Ying Pun stations. The museum is open Tuesday to Saturday, 10 am to 5 pm, and Sunday and public holidays are open until 5 pm. Be prepared for a walk up a hill to reach the museum.
A8: acwd007 | B8: Lan Kwai Fong | C8: =IF($A8<>"", _xlfn.IFNA(VLOOKUP(RIGHT(LEFT($A8,4),3),'District LookUp Table'!$A$2:$B$19,2,FALSE), "NOT FOUND"), "") -> Central & Western | D8: 22.280879, 114.155398 | E8: Recreation & Activities | F8: Chill | G8: Indoor | H8: Tourist Friendly, Solo Travelers | I8: Lan Kwai Fong is a vibrant, energetic hub in Hong Kong's Central district, known for its diverse range of bars, clubs, and restaurants. It's a popular destination for tourists and locals alike, offering a lively atmosphere and a wide selection of entertainment. The area is known for its pubs, and a historic prison is located nearby. | J8: The area boasts a wide array of amenities, including numerous bars, nightclubs, cocktail bars, and restaurants. Visitors can easily access MTR stations, including Central Station Exit D1, and walk along Pedder Street and Wyndham Street. Taxi services are readily available. There are also art galleries and restaurants to visit during the day. | K8: For a truly immersive experience, explore the area after 9:30 PM, especially on Friday and Saturday nights. Be prepared for crowds and a high level of energy. If you're looking for a relaxing evening, consider visiting during the day to explore the local art galleries and restaurants. Be aware of the potential for sleazy behavior and prioritize your safety. Enjoy the vibrant nightlife and embrace the local culture.
A9: acwd008 | B9: Tai Kwun | C9: =IF($A9<>"", _xlfn.IFNA(VLOOKUP(RIGHT(LEFT($A9,4),3),'District LookUp Table'!$A$2:$B$19,2,FALSE), "NOT FOUND"), "") -> Central & Western | D9: 22.281552, 114.154078 | E9: Heritage & Culture | F9: Retro/Nostalgic | G9: Indoor, Budget | H9: Tourist Friendly, Family Friendly | I9: Tai Kwun, a heritage-arts venue and living record of the legal system in Hong Kong, offers a unique blend of history, art, and culture. Located in Central, it features 16 revitalized buildings, including the former Central Police Station and Magistracy, and is home to interactive exhibits and a diverse range of activities. Visitors can explore the justice system history, enjoy a mix of art, music, and theatre, and experience a vibrant atmosphere. | J9: Tai Kwun offers a variety of facilities, including shops, restaurants, exhibitions, and interactive exhibits. The complex includes 3 major heritage properties: Former Central Police Station, Former Central Magistracy, and Former Victoria Prison. Visitors can explore the former Central Police Station, the former Central Magistracy, and the former Victoria Prison, all declared monuments in Hong Kong. The complex includes a large space for exhibitions, and a variety of food and drink outlets. The complex includes a new JC Contemporary also within the compound. | K9: Visit the museum to learn about the history of the legal system and the justice system. Take a walk around the complex to see the different buildings and historical sites. Be sure to allow ample time to explore the different sections and attractions. The complex is large, so plan your route in advance.
A10: acwd009 | B10: Central Market | C10: =IF($A10<>"", _xlfn.IFNA(VLOOKUP(RIGHT(LEFT($A10,4),3),'District LookUp Table'!$A$2:$B$19,2,FALSE), "NOT FOUND"), "") -> Central & Western | D10: 22.284051, 114.155443 | E10: Urban & Architecture | F10: Local Favorites, Retro/Nostalgic | G10: Indoor | H10: Tourist Friendly, Family Friendly, Solo Travelers, Elderly Friendly | I10: Hong Kong's historic street market, once a bustling commercial hub, has been revitalized into a vibrant and engaging public space. This landmark, preserved as a 'Playground For All', now offers a unique blend of traditional heritage and modern design, attracting visitors seeking a memorable cultural experience. | J10: The market features numerous food stalls, artisanal shops, and cafes. There are several shops selling unique clothing, jewelry, and handmade goods. The ground floor offers a variety of dining options and drinks. The upper floors house exhibition spaces and quirky shops like Tiny HK. A quick link to the mid-levels escalator is readily available. | K10: Explore the market's diverse offerings, from local street food to handcrafted goods. Take your time to wander through the stalls and soak in the atmosphere. Don't be afraid to strike up conversations with vendors and locals. Enjoy a leisurely meal and a refreshing drink.
A11: acwd010 | B11: Hong Kong Zoological and Botanical Gardens | C11: =IF($A11<>"", _xlfn.IFNA(VLOOKUP(RIGHT(LEFT($A11,4),3),'District LookUp Table'!$A$2:$B$19,2,FALSE), "NOT FOUND"), "") -> Central & Western | D11: 22.277695, 114.156412 | E11: Recreation & Activities | F11: Chill, Local Favorites | G11: Outdoor, Free | H11: Family Friendly, Solo Travelers | I11: The Hong Kong Zoological and Botanical Gardens is a free to enter park and botanical garden in Hong Kong, offering a peaceful escape in the heart of the city while promoting education and conservation efforts. It features a diverse range of plants and animals, including primates, birds, and mammals, and provides a unique experience for families, tourists, and nature enthusiasts. The park is known for its beautiful greenery, wildlife, and accessible pathways. | J11: The park offers a variety of facilities, including walking paths, arboretum, and a green house. Visitors can enjoy walking around before getting on the Peak tram, observing animals and birds, and relaxing in the peaceful atmosphere. The park is hilly, so come rested. | K11: Visit during mornings and afternoons for quieter experiences. The zoo is free, and it's a great place to explore different species of animals and plants. The park is a great place to relax and escape the hustle and bustle of the city.
A12: aead001 | B12: Monster Building Spot | C12: =IF($A12<>"", _xlfn.IFNA(VLOOKUP(RIGHT(LEFT($A12,4),3),'District LookUp Table'!$A$2:$B$19,2,FALSE), "NOT FOUND"), "") -> Eastern | D12: 22.284277, 114.212469 | E12: Urban & Architecture | F12: Insta-Worthy | G12: Urban | H12: Tourist Friendly, Family Friendly | I12: The Monster Building in Quarry Bay is a striking example of high-density urban living in Hong Kong, featuring a complex of five interconnected apartments. Originally built in the 1960s as a common home, it has become an iconic photography and film location, frequently featured in Hollywood movies. It’s a popular destination for architecture enthusiasts and urban explorers, with over 2,200 apartment units and thousands of residents. | J12: Free of charge, with two entrances on King’s Road. Accessible by subway, bus, taxi, or ding ding. | K12: Allow 30 minutes to take pictures without disturbing locals. Support the locals by visiting cafes and stores in the complex. Do not disturb the locals as this is their living place.
A13: aead002 | B13: Chun Yeung Street | C13: =IF($A13<>"", _xlfn.IFNA(VLOOKUP(RIGHT(LEFT($A13,4),3),'District LookUp Table'!$A$2:$B$19,2,FALSE), "NOT FOUND"), "") -> Eastern | D13: 22.291335, 114.197828 | E13: Urban & Architecture | F13: Local Favorites | G13: Outdoor, Urban | H13: Tourist Friendly | I13: This location offers a unique experience with a wet market and tram views, particularly popular for photographers. It’s a vibrant, bustling area with a strong local atmosphere. | J13: The location features a wet market with shops and stalls, and a tramway passing through the market. MTR exit: North Point station A1 or eastbound tram heading towards the North Point terminus. | K13: Be prepared for crowds, especially during peak hours, and consider bringing cash as prices may be higher than other markets. Enjoy the atmosphere and capture some memorable photos.
... A15: aead004 | B15: Lei Yue Mun Park | C15: =IF($A15<>"", _xlfn.IFNA(VLOOKUP(RIGHT(LEFT($A15,4),3),'District LookUp Table'!$A$2:$B$19,2,FALSE), "NOT FOUND"), "") -> Eastern | D15: 22.277737, 114.232659 | E15: Nature & Scenery | F15: Chill | G15: Outdoor, Steep Terrain | H15: Family Friendly, Tourist Friendly | I15: Lei Yue Mun Park is a large park with a playground, archery, karaoke, and a horse riding school. It offers a scenic outdoor space with a steep hill. | J15: Playground, Archery, Karaoke room, Bicycle rental, Board games, Bracelet making workshop, BBQ facilities, Horseback riding school, canteen. | K15: Bring mosquito repellent, wear comfortable shoes for steep slopes, and bring your own drinks to save money. Be prepared for pricey vending machine drinks and the strict coach at the archery range.
A16: aead005 | C16: =IF($A16<>"", _xlfn.IFNA(VLOOKUP(RIGHT(LEFT($A16,4),3),'District LookUp Table'!$A$2:$B$19,2,FALSE), "NOT FOUND"), "") -> Eastern
A17: aisd001 | B17: Pui O Beach | C17: =IF($A17<>"", _xlfn.IFNA(VLOOKUP(RIGHT(LEFT($A17,4),3),'District LookUp Table'!$A$2:$B$19,2,FALSE), "NOT FOUND"), "") -> Islands | D17: 22.238876, 113.978691 | E17: Recreation & Activities | F17: Chill, Local Favorites | G17: Outdoor | H17: Tourist Friendly | I17: Pui O Beach, located on the south side of Lantau Island, offers a relaxing experience with a mix of black and yellow sand, a popular weekend destination, and opportunities for swimming, camping, and exploring the surrounding landscape. | J17: Facilities include Beach, Lifeguard Station, Beach Shack Cafe, Rental, and Camping. | K17: Visit during the off-season for fewer crowds. Bring sunscreen and a hat. Be mindful of the mud on the beach. Check the beach's status before heading there. Enjoy the scenic views and the local culture.
A18: aisd002 | B18: Tai O | C18: =IF($A18<>"", _xlfn.IFNA(VLOOKUP(RIGHT(LEFT($A18,4),3),'District LookUp Table'!$A$2:$B$19,2,FALSE), "NOT FOUND"), "") -> Islands | D18: 22.254151, 113.862149 | E18: Nature & Scenary | F18: Local Favorites, Hidden | G18: Outdoor | H18: Tourist Friendly | I18: Tai O is a charming fishing village in Hong Kong, offering a glimpse into traditional life. Located near the Big Buddha, it features stilts over the water and a unique atmosphere. Visitors can easily access the village via bus from the Big Buddha and ca, and enjoy boat rides to see pink dolphins. The village is known for its fish products, curried fish balls, and local sauces. | J18: Bus services connect Tai O to the Big Buddha. Boat rides are available to see pink dolphins. | K18: Explore the village on foot, try the local curried fish balls and sauces, and take advantage of the boat rides to see the pink dolphins. Be prepared for a slower pace of travel due to the village's size.
A19: aisd003 | B19: Citygate Outlets | C19: =IF($A19<>"", _xlfn.IFNA(VLOOKUP(RIGHT(LEFT($A19,4),3),'District LookUp Table'!$A$2:$B$19,2,FALSE), "NOT FOUND"), "") -> Islands | D19: 22.289652, 113.941258 | E19: Shopping | F19: Local Favorites | G19: Indoor | H19: Tourist Friendly | I19: Citygate Outlets is a large shopping mall located near an airport, offering a wide variety of retail outlets, food options, and amenities. It features air conditioning, numerous shops, and convenient transportation links to the city center. | J19: The mall features MTR exits, bus routes, and ample space for walking. There are restrooms available. Nearby apartments are also available for those needing a place to stay. | K19: For efficient travel, utilize the MTR station nearby. Be prepared for crowds, especially during peak hours. Check for deals and promotions on various shops.
A20: aisd004 | C20: =IF($A20<>"", _xlfn.IFNA(VLOOKUP(RIGHT(LEFT($A20,4),3),'District LookUp Table'!$A$2:$B$19,2,FALSE), "NOT FOUND"), "") -> Islands
A21: aisd005 | C21: =IF($A21<>"", _xlfn.IFNA(VLOOKUP(RIGHT(LEFT($A21,4),3),'District LookUp Table'!$A$2:$B$19,2,FALSE), "NOT FOUND"), "") -> Islands
A22: akcd001 | B22: Lung Cheung Road Sitting-out Area | C22: =IF($A22<>"", _xlfn.IFNA(VLOOKUP(RIGHT(LEFT($A22,4),3),'District LookUp Table'!$A$2:$B$19,2,FALSE), "NOT FOUND"), "") -> Kowloon City | D22: 22.342497, 114.174208 | E22: Nature & Scenery | F22: Insta-Worthy, Scenic | G22: Outdoor | H22: Tourist Friendly, Solo Travelers | I22: The Lung Cheung Road Observatory is a small location offering panoramic city views. It provides a stunning vista of the skyline framed by mountains and greenery, particularly impressive during both daytime and nighttime. The area is known for its unobstructed views and peaceful atmosphere. Visitors can easily access this vantage point. | J22: The Lung Cheung Road Observatory offers sweeping, unobstructed views of the city skyline. Transportation options include taking a bus directly to the Phoenix House stop, or a 15-minute uphill walk from the Moonbeam Terrace bus stop. | K22: Bring a camera to capture the stunning views. Consider visiting after dark for the best nighttime panorama. Be prepared for a slightly challenging uphill walk if taking the bus route alighting at Moonbeam Terrace.
A23: akcd002 | B23: Kowloon Walled City Park | C23: =IF($A23<>"", _xlfn.IFNA(VLOOKUP(RIGHT(LEFT($A23,4),3),'District LookUp Table'!$A$2:$B$19,2,FALSE), "NOT FOUND"), "") -> Kowloon City | E23: Heritage & Culture | F23: Hidden, Local Favorites | G23: Outdoor | H23: Tourist Friendly, Solo Travelers, Elderly Friendly | I23: Kowloon Walled Park is a historical park in Hong Kong, representing a unique territory with a complex past. The park incorporates restored former houses and offers a glimpse into the city's history. It provides a peaceful escape from the city's bustle, featuring landscaped gardens and traditional Chinese design. The park’s size is considerable, offering ample space for exploration and relaxation. | J23: Visitors can access the park by taking the subway to Sung Wong Toi then exit from B3, then walking two gates. A free exhibition from the movie Walled in, twilight of the warriors is available, but requires timed tickets. The park includes a basketball court, soccer court, and a cycling area. Traditional Chinese garden design, winding paths, ponds, and pavilions are present within the park. | K23: Walled in exhibition is free. Consider visiting during quieter times to avoid crowds and enjoy a more peaceful experience. The park is well-maintained and offers a pleasant walking experience.
A24: akcd003 | B24: Kai Tak Sports Park | C24: =IF($A24<>"", _xlfn.IFNA(VLOOKUP(RIGHT(LEFT($A24,4),3),'District LookUp Table'!$A$2:$B$19,2,FALSE), "NOT FOUND"), "") -> Kowloon City | E24: Recreation & Activities | F24: Chill, Insta-Worthy | G24: Outdoor | H24: Tourist Friendly, Family Friendly, Solo Travelers | I24: Kai Tak Sports Park is a large open space developed from the former Kai Tak Airport Grounds. It encompasses sports facilities, residential towers, restaurants, and malls, spanning a significant area between Sung Wong Toi and Kai Tak MTR Stations. The park features a 10,000-capacity sports ground and a 50,000-seat stadium. The area offers a blend of recreational activities, shopping, and dining options, creating a vibrant and modern atmosphere. | J24: Visitors can access the park by exiting Kai Tak Station on the Tuen Ma Line. It involves a considerable walk due to the expansive area. The park includes large-scale sculptures, fountain pools, benches, and covered walkways for shade and protection from the elements. Several malls are located around the area, offering a variety of food choices. Public toilets are available within the area. The waterfront is beginning to open, utilizing the old airport runway and extending to the adjacent cruise terminal. | K24: Visitors should be prepared for a long walk from the MTR exits. The malls are good places to cool down on hot summer days. Locals frequently visit the park for walks and dog-walking.
A25: akcd004 | C25: =IF($A25<>"", _xlfn.IFNA(VLOOKUP(RIGHT(LEFT($A25,4),3),'District LookUp Table'!$A$2:$B$19,2,FALSE), "NOT FOUND"), "") -> Kowloon City
A26: akcd005 | C26: =IF($A26<>"", _xlfn.IFNA(VLOOKUP(RIGHT(LEFT($A26,4),3),'District LookUp Table'!$A$2:$B$19,2,FALSE), "NOT FOUND"), "") -> Kowloon City
A27: aktd001 | B27: Laguna Park | C27: =IF($A27<>"", _xlfn.IFNA(VLOOKUP(RIGHT(LEFT($A27,4),3),'District LookUp Table'!$A$2:$B$19,2,FALSE), "NOT FOUND"), "") -> Kwun Tong | E27: Nature & Scenery | F27: Chill, Local Favorites | G27: Outdoor | H27: Family Friendly, Elderly Friendly, Solo Travelers | I27: Laguna Park is a large neighborhood park situated adjacent to Laguna City, serving a residential community of over 20,000 people. It offers a green space for recreation and relaxation, featuring jogging tracks and fitness equipment. The park’s origins date back to 1991 as part of a housing development marketing campaign. While functional, it doesn’t offer extraordinary features and can be crowded during peak times. | J27: The park includes a children’s playground, jogging track, fitness equipment, benches, public restrooms, and smaller water fountains. There are trees providing shade. Access to the park is available via local residential streets. | K27: Ask the staff to heat up your pastry, and avoid visiting during peak hours if you dislike loud music.
A28: aktd002 | B28: Jordan Valley Park | C28: =IF($A28<>"", _xlfn.IFNA(VLOOKUP(RIGHT(LEFT($A28,4),3),'District LookUp Table'!$A$2:$B$19,2,FALSE), "NOT FOUND"), "") -> Kwun Tong | E28: Recreation & Activities | F28: Chill, Local Favorites | G28: Outdoor | H28: Tourist Friendly, Family Friendly, Solo Travelers | I28: Jordan Valley Park is a large park offering green spaces and recreational activities. It features expansive lawns, a model car racing track, and a family-friendly climbing trail. The park provides a relaxing escape from the city, with well-maintained facilities and ample space for various activities. It’s a popular spot for families and individuals seeking outdoor recreation. | J28: The park has two central lawns suitable for running and relaxing, and it includes running trails with varying routes and inclines. There is a remote car circuit for children to enjoy, and the Jordan Valley Morning Trail provides a family-friendly climbing experience. The park also offers a car park. | K28: Ask the staff to heat up your pastry, and avoid visiting during peak hours if you dislike loud music. The car park can be limited, and visitors may need to park at the police apartments if it is full.
A29: aktd003 | C29: =IF($A29<>"", _xlfn.IFNA(VLOOKUP(RIGHT(LEFT($A29,4),3),'District LookUp Table'!$A$2:$B$19,2,FALSE), "NOT FOUND"), "") -> Kwun Tong
A30: aktd004 | C30: =IF($A30<>"", _xlfn.IFNA(VLOOKUP(RIGHT(LEFT($A30,4),3),'District LookUp Table'!$A$2:$B$19,2,FALSE), "NOT FOUND"), "") -> Kwun Tong
A31: aktd005 | C31: =IF($A31<>"", _xlfn.IFNA(VLOOKUP(RIGHT(LEFT($A31,4),3),'District LookUp Table'!$A$2:$B$19,2,FALSE), "NOT FOUND"), "") -> Kwun Tong
A32: akwd001 | B32: Central Kwai Chung Park | C32: =IF($A32<>"", _xlfn.IFNA(VLOOKUP(RIGHT(LEFT($A32,4),3),'District LookUp Table'!$A$2:$B$19,2,FALSE), "NOT FOUND"), "") -> Kwai Tsing | E32: Nature & Scenery | F32: Hidden, Local Favorites | G32: Outdoor | H32: Tourist Friendly, Family Friendly, Solo Travelers | I32: Central Kwai Chung Park is a hidden park located in the industrial district of Hong Kong. It offers walking trails, sports courts, and shaded areas, providing a peaceful escape from the urban environment. The park boasts rich biodiversity and interesting historical features. It’s an oasis of nature within the city. | J32: The park offers functional facilities, including two water dispensers and toilets. However, the walls on the sports courts are noted to be quite short. There are many little paths and places to explore within the park. | K32: Avoid visiting during peak hours if you dislike loud music. Be aware of mosquitoes and consider bringing repellent. The park is suitable for easy hiking and jogging.
A33: akwd002 | B33: Kwai Chung Plaza | C33: =IF($A33<>"", _xlfn.IFNA(VLOOKUP(RIGHT(LEFT($A33,4),3),'District LookUp Table'!$A$2:$B$19,2,FALSE), "NOT FOUND"), "") -> Kwai Tsing | E33: Shopping | F33: Bustling, Local Favorites | G33: Indoor | H33: Tourist Friendly, Solo Travelers, Budget | I33: Kwai Chung Plaza is a small, unique shopping venue located outside the Kwai Fong MTR Station. It offers a vibrant and lively atmosphere with hundreds of small, locally-owned shops and kiosks. The plaza is known for its budget-friendly prices and a diverse selection of goods, reminiscent of shopping in Southeast Asian cities. It’s a bustling and welcoming space for shoppers seeking a different experience. | J33: Kwai Chung Plaza is an indoor shopping venue accessible via the Kwai Fong MTR Station (exit D). The property opened in 1990 and features multiple floors, offering a variety of shops and eateries. There are several floors with food shops and a level selling fresh food such as vegetables and fruits. The plaza can be incredibly crowded, and while some recognizable brand name retailers and casual eateries are present, most of the businesses are locally owned. Taxi availability is assumed, but specific details are not mentioned. | K33: Be prepared for crowds and potential noise. Haggling is expected when shopping at the kiosks. This plaza offers a unique shopping experience, reminiscent of Southeast Asian markets, and is a good option for budget-conscious shoppers.
A34: akwd003 | C34: =IF($A34<>"", _xlfn.IFNA(VLOOKUP(RIGHT(LEFT($A34,4),3),'District LookUp Table'!$A$2:$B$19,2,FALSE), "NOT FOUND"), "") -> Kwai Tsing
A35: akwd004 | C35: =IF($A35<>"", _xlfn.IFNA(VLOOKUP(RIGHT(LEFT($A35,4),3),'District LookUp Table'!$A$2:$B$19,2,FALSE), "NOT FOUND"), "") -> Kwai Tsing
A36: akwd005 | C36: =IF($A36<>"", _xlfn.IFNA(VLOOKUP(RIGHT(LEFT($A36,4),3),'District LookUp Table'!$A$2:$B$19,2,FALSE), "NOT FOUND"), "") -> Kwai Tsing
A37: anod001 | B37: Sha Tau Kok | C37: =IF($A37<>"", _xlfn.IFNA(VLOOKUP(RIGHT(LEFT($A37,4),3),'District LookUp Table'!$A$2:$B$19,2,FALSE), "NOT FOUND"), "") -> North | E37: Nature & Scenery | F37: Insta-Worthy, Hidden | G37: Outdoor | H37: Tourist Friendly, Solo Travelers | I37: Located at the border between the North District of the New Territories in Hong Kong and the Yantian District of Shenzhen in the Mainland, Sha Tau Kok was once a Frontier Closed Area. Following its opening, it has now become a popular destination for day trips, requiring a Closed Area Permit for entry. The first and second phases of Sha Tau Kok Pier have opened, providing transportation options for both individual travelers and day-trip tour groups. The area features spectacular coastlines and unique historical landmarks, such as vintage road signs and the Sun Moon Pavilion. Sha Tau Kok is renowned for its beautiful sea views and cultural history. | J37: Sha Tau Kok Pier is 280 meters long; originally built in the 1960s and later reconstructed in 2004, it is only a 20 to 30-minute boat ride from Kat O and Ap Chau. The pier promenade is a choice for romantic strolls. At the end of the pier, "The Ends of the Earth" paired with a pure white lighthouse offers beautiful scenery. Shun Ping Street features murals on the walls painted by Sha Tau Kok primary school students. At the end of the pier, "The Ends of the Earth" paired with a pure white lighthouse offers beautiful scenery. The Old Sha Tau Kok Fire Station is a distinctive landmark of Sha Tau Kok, preserving its former appearance and displaying a 1:1 replica of a century-old hand-drawn fire engine. Chung Ying Street is located at the border and was once a trading center for Hong Kong merchants during the early Reform and Opening-up period; it is now a site of historical witness, featuring a wishing lookout and a garden modeled after the style of old Hong Kong railway stations. | K37: Apply for a Closed Area Permit to visit Sha Tau Kok. Kaito ferries are available to reach tourist hotspots such as Lai Chi Wo, Kat O, and Ap Chau. Consider avoiding peak hours to avoid crowds. Sha Tau Kok Pier offers a romantic walking route, featuring murals by Sha Tau Kok primary school students on the walls. Enjoy the lighthouse and sea views at "The Ends of the Earth." The Old Sha Tau Kok Fire Station displays a vintage fire engine and is a great spot for photos. Chung Ying Street Garden provides an opportunity to view Chung Ying Street and allows for hanging wishing plaques.
A38: anod002 | B38: Long Valley Nature Centre | C38: =IF($A38<>"", _xlfn.IFNA(VLOOKUP(RIGHT(LEFT($A38,4),3),'District LookUp Table'!$A$2:$B$19,2,FALSE), "NOT FOUND"), "") -> North
A39: anod003 | C39: =IF($A39<>"", _xlfn.IFNA(VLOOKUP(RIGHT(LEFT($A39,4),3),'District LookUp Table'!$A$2:$B$19,2,FALSE), "NOT FOUND"), "") -> North
A40: anod004 | C40: =IF($A40<>"", _xlfn.IFNA(VLOOKUP(RIGHT(LEFT($A40,4),3),'District LookUp Table'!$A$2:$B$19,2,FALSE), "NOT FOUND"), "") -> North
A41: anod005 | C41: =IF($A41<>"", _xlfn.IFNA(VLOOKUP(RIGHT(LEFT($A41,4),3),'District LookUp Table'!$A$2:$B$19,2,FALSE), "NOT FOUND"), "") -> North
A42: askd001 | B42: Tap Mun | C42: =IF($A42<>"", _xlfn.IFNA(VLOOKUP(RIGHT(LEFT($A42,4),3),'District LookUp Table'!$A$2:$B$19,2,FALSE), "NOT FOUND"), "") -> Sai Kung
A43: askd002 | B43: UNESCO Global Geopark | C43: =IF($A43<>"", _xlfn.IFNA(VLOOKUP(RIGHT(LEFT($A43,4),3),'District LookUp Table'!$A$2:$B$19,2,FALSE), "NOT FOUND"), "") -> Sai Kung
A44: askd003 | B44: High Island Reservoir East Dam | C44: =IF($A44<>"", _xlfn.IFNA(VLOOKUP(RIGHT(LEFT($A44,4),3),'District LookUp Table'!$A$2:$B$19,2,FALSE), "NOT FOUND"), "") -> Sai Kung | E44: Nature & Scenery | F44: Insta-Worthy, Hidden | G44: Outdoor | H44: Tourist Friendly, Solo Travelers, Elderly Friendly | I44: High Island Reservoir and its surrounding Sai Kung East Country Park area offer stunning natural beauty and a peaceful escape from city life. The reservoir is massive, featuring breathtaking views of turquoise water, rugged coastline, and unique hexagonal rock columns. It’s a popular destination for nature lovers and hikers, providing a different side of Hong Kong. The area is known for its scenic trails and diverse landscapes. It’s a large area with a mix of easy and challenging walking routes. | J44: There are limited facilities available at High Island Reservoir. Transportation options include public buses and green taxis; a bus change is required, and the final leg involves a 30-minute taxi ride from the northeast of Hong Kong. The area offers views of the dam, island, cave, and lava columns. | K44: Bring enough water and snacks as facilities are limited. Consider visiting during sunrise or sunset for optimal photography opportunities. The area is easily accessible by taxi or public transportation (minibus change required). It’s a good starting point for longer or more challenging hikes.
A45: askd004 | B45: Green Egg Island | C45: =IF($A45<>"", _xlfn.IFNA(VLOOKUP(RIGHT(LEFT($A45,4),3),'District LookUp Table'!$A$2:$B$19,2,FALSE), "NOT FOUND"), "") -> Sai Kung
A46: askd005 | C46: =IF($A46<>"", _xlfn.IFNA(VLOOKUP(RIGHT(LEFT($A46,4),3),'District LookUp Table'!$A$2:$B$19,2,FALSE), "NOT FOUND"), "") -> Sai Kung
A47: asod001 | B47: Cape Collision Battery | C47: =IF($A47<>"", _xlfn.IFNA(VLOOKUP(RIGHT(LEFT($A47,4),3),'District LookUp Table'!$A$2:$B$19,2,FALSE), "NOT FOUND"), "") -> Southern | E47: Nature & Scenery | F47: Hidden, Insta-Worthy | G47: Outdoor, Steep Terrain | H47: Tourist Friendly, Solo Travelers | I47: Cape Collinson Battery is a hidden gem offering panoramic ocean views and sea cliffs. It’s a peaceful escape from the city, suitable for short adventures or quiet strolls. The location is accessible via a trail, though it requires some climbing. The area is relatively small and offers a unique perspective of the coastline. | J47: There is no official trail to the battery, but steps have been added to the fence marking the trail-head. Access requires a 30-minute walk from Siu Sai Wan to Big Wave Bay. The path to the battery is a hiking trail, and the area can be a bit less maintained. Be cautious when exploring the battery due to recent damage and rocks from a typhoon. | K47: Bring enough water and proper footwear for the hike. Use mosquito repellent, especially on hot days. Consider visiting on a weekday to avoid crowds. Be careful when exploring the battery due to recent damage.
A48: asod002 | B48: Tai Tam Tuk Reservoir Dam Viewpoint | C48: =IF($A48<>"", _xlfn.IFNA(VLOOKUP(RIGHT(LEFT($A48,4),3),'District LookUp Table'!$A$2:$B$19,2,FALSE), "NOT FOUND"), "") -> Southern | E48: Nature & Scenery | F48: Chill, Hidden | G48: Outdoor, Budget, Free | H48: Tourist Friendly, Family Friendly, Solo Travelers | I48: This location is a large reservoir situated in the Tai Tam Valley and Country Park on Hong Kong Island. It offers a peaceful escape from the city, characterized by greenery, waterfalls, and a dam. The area is known for its scenic beauty and historical waterworks structures. It is a popular destination for both locals and tourists seeking a relaxing experience. | J48: Visitors can access the reservoir via a casual and easy hike through the Tai Tam Waterworks Heritage Trail, starting from the south entrance or the northern entrance. Toilets, a water refill station, and drink machines are located at the south entrance. There are also a few BBQ spots along the Tai Tam Tuk reservoirs for picnics. Bus route 14 stops at Tai Tam Reservoir North to facilitate access. | K48: The reservoir is particularly impressive after heavy rainfall, showcasing the dam in full swing. Consider visiting during good weather for optimal photography. Explore Tai Tam Tuk Village for a peaceful experience. You can choose different routes to reach the reservoir depending on your starting point.
A49: asod003 | B49: Stanley Murray House | C49: =IF($A49<>"", _xlfn.IFNA(VLOOKUP(RIGHT(LEFT($A49,4),3),'District LookUp Table'!$A$2:$B$19,2,FALSE), "NOT FOUND"), "") -> Southern
A50: asod004 | B50: Hong Kong Correctional Services Museum | C50: =IF($A50<>"", _xlfn.IFNA(VLOOKUP(RIGHT(LEFT($A50,4),3),'District LookUp Table'!$A$2:$B$19,2,FALSE), "NOT FOUND"), "") -> Southern
A51: asod005 | B51: Waterfall Bay Park | C51: =IF($A51<>"", _xlfn.IFNA(VLOOKUP(RIGHT(LEFT($A51,4),3),'District LookUp Table'!$A$2:$B$19,2,FALSE), "NOT FOUND"), "") -> Southern
A52: assp001 | B52: Ap Liu Street | C52: =IF($A52<>"", _xlfn.IFNA(VLOOKUP(RIGHT(LEFT($A52,4),3),'District LookUp Table'!$A$2:$B$19,2,FALSE), "NOT FOUND"), "") -> Sham Shui Po
A53: assp002 | B53: Golden Computer Arcade | C53: =IF($A53<>"", _xlfn.IFNA(VLOOKUP(RIGHT(LEFT($A53,4),3),'District LookUp Table'!$A$2:$B$19,2,FALSE), "NOT FOUND"), "") -> Sham Shui Po
A54: assp003 | C54: =IF($A54<>"", _xlfn.IFNA(VLOOKUP(RIGHT(LEFT($A54,4),3),'District LookUp Table'!$A$2:$B$19,2,FALSE), "NOT FOUND"), "") -> Sham Shui Po
A55: assp004 | C55: =IF($A55<>"", _xlfn.IFNA(VLOOKUP(RIGHT(LEFT($A55,4),3),'District LookUp Table'!$A$2:$B$19,2,FALSE), "NOT FOUND"), "") -> Sham Shui Po
A56: assp005 | C56: =IF($A56<>"", _xlfn.IFNA(VLOOKUP(RIGHT(LEFT($A56,4),3),'District LookUp Table'!$A$2:$B$19,2,FALSE), "NOT FOUND"), "") -> Sham Shui Po
A57: astd001 | B57: Ten Thousand Buddhas Monastery | C57: =IF($A57<>"", _xlfn.IFNA(VLOOKUP(RIGHT(LEFT($A57,4),3),'District LookUp Table'!$A$2:$B$19,2,FALSE), "NOT FOUND"), "") -> Sha Tin
A58: astd002 | B58: Kam Shan Country Park | C58: =IF($A58<>"", _xlfn.IFNA(VLOOKUP(RIGHT(LEFT($A58,4),3),'District LookUp Table'!$A$2:$B$19,2,FALSE), "NOT FOUND"), "") -> Sha Tin
A59: astd003 | B59: Hong Kong Heritage Museum | C59: =IF($A59<>"", _xlfn.IFNA(VLOOKUP(RIGHT(LEFT($A59,4),3),'District LookUp Table'!$A$2:$B$19,2,FALSE), "NOT FOUND"), "") -> Sha Tin
A60: astd004 | B60: Ngong Ping Viewing Point | C60: =IF($A60<>"", _xlfn.IFNA(VLOOKUP(RIGHT(LEFT($A60,4),3),'District LookUp Table'!$A$2:$B$19,2,FALSE), "NOT FOUND"), "") -> Sha Tin
A61: astd005 | B61: GO PARK Sai Sha | C61: =IF($A61<>"", _xlfn.IFNA(VLOOKUP(RIGHT(LEFT($A61,4),3),'District LookUp Table'!$A$2:$B$19,2,FALSE), "NOT FOUND"), "") -> Sha Tin
A62: atmd001 | B62: Ho Wo Street | C62: =IF($A62<>"", _xlfn.IFNA(VLOOKUP(RIGHT(LEFT($A62,4),3),'District LookUp Table'!$A$2:$B$19,2,FALSE), "NOT FOUND"), "") -> Tuen Mun | D62: 22.357358, 113.953006 | E62: Nature & Scenary
A63: atmd002 | B63: T·PARK | C63: =IF($A63<>"", _xlfn.IFNA(VLOOKUP(RIGHT(LEFT($A63,4),3),'District LookUp Table'!$A$2:$B$19,2,FALSE), "NOT FOUND"), "") -> Tuen Mun | D63: 22.422296, 113.924178 | E63: Urban & Architecture
A64: atmd003 | B64: Hong Kong Golden Beach | C64: =IF($A64<>"", _xlfn.IFNA(VLOOKUP(RIGHT(LEFT($A64,4),3),'District LookUp Table'!$A$2:$B$19,2,FALSE), "NOT FOUND"), "") -> Tuen Mun | D64: 22.371299, 113.988551 | E64: Recreation & Activities
A65: atmd004 | B65: Reservoir Islands Viewpoint | C65: =IF($A65<>"", _xlfn.IFNA(VLOOKUP(RIGHT(LEFT($A65,4),3),'District LookUp Table'!$A$2:$B$19,2,FALSE), "NOT FOUND"), "") -> Tuen Mun | D65: 22.390823, 114.024112 | E65: Nature & Scenary | H65: Hiking
A66: atmd005 | C66: =IF($A66<>"", _xlfn.IFNA(VLOOKUP(RIGHT(LEFT($A66,4),3),'District LookUp Table'!$A$2:$B$19,2,FALSE), "NOT FOUND"), "") -> Tuen Mun
A67: atpd001 | B67: Tung Ping Chau | C67: =IF($A67<>"", _xlfn.IFNA(VLOOKUP(RIGHT(LEFT($A67,4),3),'District LookUp Table'!$A$2:$B$19,2,FALSE), "NOT FOUND"), "") -> Tai Po
A68: atpd002 | B68: Tai Mei Tuk | C68: =IF($A68<>"", _xlfn.IFNA(VLOOKUP(RIGHT(LEFT($A68,4),3),'District LookUp Table'!$A$2:$B$19,2,FALSE), "NOT FOUND"), "") -> Tai Po
A69: atpd003 | C69: =IF($A69<>"", _xlfn.IFNA(VLOOKUP(RIGHT(LEFT($A69,4),3),'District LookUp Table'!$A$2:$B$19,2,FALSE), "NOT FOUND"), "") -> Tai Po
A70: atpd004 | C70: =IF($A70<>"", _xlfn.IFNA(VLOOKUP(RIGHT(LEFT($A70,4),3),'District LookUp Table'!$A$2:$B$19,2,FALSE), "NOT FOUND"), "") -> Tai Po
A71: atpd005 | C71: =IF($A71<>"", _xlfn.IFNA(VLOOKUP(RIGHT(LEFT($A71,4),3),'District LookUp Table'!$A$2:$B$19,2,FALSE), "NOT FOUND"), "") -> Tai Po
A72: atwd001 | C72: =IF($A72<>"", _xlfn.IFNA(VLOOKUP(RIGHT(LEFT($A72,4),3),'District LookUp Table'!$A$2:$B$19,2,FALSE), "NOT FOUND"), "") -> Tsuen Wan
A73: atwd002 | C73: =IF($A73<>"", _xlfn.IFNA(VLOOKUP(RIGHT(LEFT($A73,4),3),'District LookUp Table'!$A$2:$B$19,2,FALSE), "NOT FOUND"), "") -> Tsuen Wan
A74: atwd003 | C74: =IF($A74<>"", _xlfn.IFNA(VLOOKUP(RIGHT(LEFT($A74,4),3),'District LookUp Table'!$A$2:$B$19,2,FALSE), "NOT FOUND"), "") -> Tsuen Wan
A75: atwd004 | C75: =IF($A75<>"", _xlfn.IFNA(VLOOKUP(RIGHT(LEFT($A75,4),3),'District LookUp Table'!$A$2:$B$19,2,FALSE), "NOT FOUND"), "") -> Tsuen Wan
A76: atwd005 | C76: =IF($A76<>"", _xlfn.IFNA(VLOOKUP(RIGHT(LEFT($A76,4),3),'District LookUp Table'!$A$2:$B$19,2,FALSE), "NOT FOUND"), "") -> Tsuen Wan
A77: awcd001 | C77: =IF($A77<>"", _xlfn.IFNA(VLOOKUP(RIGHT(LEFT($A77,4),3),'District LookUp Table'!$A$2:$B$19,2,FALSE), "NOT FOUND"), "") -> Wan Chai
A78: awcd002 | C78: =IF($A78<>"", _xlfn.IFNA(VLOOKUP(RIGHT(LEFT($A78,4),3),'District LookUp Table'!$A$2:$B$19,2,FALSE), "NOT FOUND"), "") -> Wan Chai
A79: awcd003 | C79: =IF($A79<>"", _xlfn.IFNA(VLOOKUP(RIGHT(LEFT($A79,4),3),'District LookUp Table'!$A$2:$B$19,2,FALSE), "NOT FOUND"), "") -> Wan Chai
A80: awcd004 | C80: =IF($A80<>"", _xlfn.IFNA(VLOOKUP(RIGHT(LEFT($A80,4),3),'District LookUp Table'!$A$2:$B$19,2,FALSE), "NOT FOUND"), "") -> Wan Chai
... A86: awts005 | C86: =IF($A86<>"", _xlfn.IFNA(VLOOKUP(RIGHT(LEFT($A86,4),3),'District LookUp Table'!$A$2:$B$19,2,FALSE), "NOT FOUND"), "") -> Wong Tai Sin
A87: ayld001 | B87: Kingswood Richly Plaza | C87: =IF($A87<>"", _xlfn.IFNA(VLOOKUP(RIGHT(LEFT($A87,4),3),'District LookUp Table'!$A$2:$B$19,2,FALSE), "NOT FOUND"), "") -> Yuen Long | D87: 22.452153, 114.000390 | E87: Food & Drink | K87: A short walk from MTR Tin Shui Wai Station or the Locwood Light Rail stop brings you to Kingswood Richly Plaza, a cornerstone of daily life for local residents. Unlike the polished, corporate malls typically found in Hong Kong, "Richly" is a maze of small, independently owned stalls and narrow corridors that hum with a distinct, "down-to-earth" energy. It is often described as the "vernacular heart" of the district, offering a stark contrast to the standardized, high-end shopping centers nearby. The plaza is particularly famous as a street food sanctuary. Students and families frequent the first and second floors for affordable snacks, ranging from spicy Sichuan noodles and tofu fa to creative fusion pancakes and Hong Kong-style "cart noodles." Beyond food, the mall is a dense ecosystem of essential services—tucked away in its winding corners, you'll find family clinics, local hair salons, hardware stores, and tiny boutiques selling everything from trendy phone cases to traditional dried goods. For many in Tin Shui Wai, it is more than just a place to shop; it is a vital community hub where the atmosphere is busy, unpretentious, and deeply rooted in the neighborhood's history.
A88: ayld002 | B88: Ha Pak Nai | C88: =IF($A88<>"", _xlfn.IFNA(VLOOKUP(RIGHT(LEFT($A88,4),3),'District LookUp Table'!$A$2:$B$19,2,FALSE), "NOT FOUND"), "") -> Yuen Long | D88: 22.4267459, 113.9430758 | E88: Nature & Scenary | H88: Romantic, Insta-Worthy, Scenic, Local Favorites | K88: Located just to the west of Lau Fau Shan is Ha Pak Nai, widely celebrated as the premier spot in Hong Kong for witnessing the sunset. As the tide recedes, the vast mudflats transform into a natural mirror, reflecting the sky's shifting colors in the shallow, still waters. The landscape is dotted with dense mangroves and weathered oyster beds, forming a unique ecosystem that serves as a sanctuary for rare horseshoe crabs and migratory birds. Looking across Deep Bay, the towering skyscrapers of Shenzhen's Shekou district create a striking contrast against the tranquil coastline. Beyond its natural beauty, the area holds significant historical weight; hidden within the village is a fortified structure dating back to the 1911 Revolution, now a declared monument. Unlike the bustling seafood markets nearby, Ha Pak Nai offers a quiet, reflective atmosphere where the rhythm of the tides and the history of the frontier converge.
A89: ayld003 | B89: Lau Fau Shan | C89: =IF($A89<>"", _xlfn.IFNA(VLOOKUP(RIGHT(LEFT($A89,4),3),'District LookUp Table'!$A$2:$B$19,2,FALSE), "NOT FOUND"), "") -> Yuen Long | D89: 22.4673801, 113.9841334 | E89: Food & Drink | H89: Hidden, Chill | K89: About 20 minutes by double-decker bus or minibus from MTR Tin Shui Wai Station lies Lau Fau Shan, a seafood town overlooking Shenzhen in Mainland China.After hopping off the bus and wandering down a narrow alleyway, you'll find yourself flanked by a dense row of seafood restaurants and shops selling fresh catches and dried goods. As you emerge from the passage, the view suddenly opens up to the sea. There is a large square where the skyline of Shenzhen's skyscrapers stretches across the water. To your left, you can see the Shenzhen Bay Bridge spanning the waves, which carries travelers by car to the immigration checkpoint in western Shenzhen. The square also features a sculpture of an oyster—the local specialty—making it a perfect "Instagrammable" spot. Along the alley you walked through, you can enjoy ginger-infused sweets and tofu fa (tofu pudding) in addition to seafood, making it a great place for a quick break. It is a town that offers a seafood experience with a vibe quite distinct from the outlying islands or Sai Kung. While the town remains famous for its seafood restaurants today, the local oysters have lost some of their former glory, reportedly due to pollution from the Shenzhen side. Right nearby, vast wetlands stretch across the landscape, and there is an observation deck on the hill of Lau Fau Shan where you can look out over the entire marshy expanse. With Shenzhen situated directly on the opposite bank, you can clearly see the buildings on the other side with the naked eye.
A90: ayld004 | B90: Nam Sang Wai Cable Ferry | C90: =IF($A90<>"", _xlfn.IFNA(VLOOKUP(RIGHT(LEFT($A90,4),3),'District LookUp Table'!$A$2:$B$19,2,FALSE), "NOT FOUND"), "") -> Yuen Long | D90: 22.453904, 114.034803 | E90: Recreation & Activities | H90: Tourist Friendly, Chill, Local Favorites, Hidden | K90: The only manual ferry in hong kong, recommended for cyclists
A91: ayld005 | B91: Tai Tong Country Park | C91: =IF($A91<>"", _xlfn.IFNA(VLOOKUP(RIGHT(LEFT($A91,4),3),'District LookUp Table'!$A$2:$B$19,2,FALSE), "NOT FOUND"), "") -> Yuen Long | D91: 22.40922, 114.03178 | E91: Nature & Scenary | H91: Tourist Friendly, Hiking | K91: Situated in the southern reaches of Yuen Long, Tai Tong Country Park serves as a lush, sprawling escape for city dwellers and is arguably most famous for its seasonal transformation. While Hong Kong is primarily known for its tropical greenery, Tai Tong offers a rare spectacle of "autumn red." Every year between December and January, the Sweet Gum Woods (Liquidambar formosana) along the Tai Tong Shan Road turn various shades of amber, orange, and deep crimson. This phenomenon draws thousands of visitors who come to witness the maple-like foliage, making the narrow road a vibrant, bustling promenade of photographers and families. Beyond the seasonal colors, the park is a gateway to the extensive Tai Lam Country Park, which is the second-largest in Hong Kong. From the Tai Tong entrance, hikers can access the final section (Section 10) of the famous MacLehose Trail, leading toward the tranquil waters of the Tai Lam Chung Reservoir, often referred to as the "Thousand Islands Lake" for its stunning archipelago-like views. The park's infrastructure is well-developed, featuring expansive barbecue pits and picnic sites shaded by towering pine and eucalyptus trees, providing a cool respite even during the humid summer months. The terrain here is accessible yet varied. For those looking for a leisurely stroll, the paved slopes of the Tai Tong Nature Trail offer educational insights into local ecology and geology. For more adventurous explorers, the connecting mountain paths lead to higher elevations, offering sweeping panoramic views of the Yuen Long Plain, the village clusters of Shap Pat Heung, and the distant skyline of Shenzhen across the border. Historically, the area was once a center for forestry and agriculture; today, the nearby Tai Tong Organic Ecopark carries on this legacy, allowing visitors to experience strawberry picking and pony rides, adding a layer of rural charm to the mountainous landscape.
A92: ayld006 | B92: Hong Kong Wetland Park | C92: =IF($A92<>"", _xlfn.IFNA(VLOOKUP(RIGHT(LEFT($A92,4),3),'District LookUp Table'!$A$2:$B$19,2,FALSE), "NOT FOUND"), "") -> Yuen Long | D92: 22.468094, 114.004183 | E92: Nature & Scenary | K92: Located on the northern edge of Tin Shui Wai in the New Territories, the Hong Kong Wetland Park is a world-class conservation, education, and tourism facility that serves as a vital ecological mitigation area for the surrounding urban development. Spanning over sixty hectares, the park is divided into a large indoor visitor center known as the Wetland Interactive World and an expansive outdoor Wetland Reserve that showcases the diversity of Hong Kong's wetland ecosystems. The journey typically begins in the visitor center, which houses themed exhibition galleries, a 3D cinema, and an indoor swamp adventure play area, providing a high-tech introduction to the importance of wetland conservation before guests venture into the natural habitats. Once outside, the park unfolds into a series of meticulously maintained environments, including the Stream Walk, the Dragonfly Pond, and the Butterfly Garden, where visitors can observe local flora and fauna in their native settings. One of the park's most famous residents is Pui Pui, a salt-water crocodile discovered in the Shan Pui River, who now lives in a dedicated outdoor enclosure designed to mimic her natural habitat. The park is particularly renowned for its Mangrove Boardwalk, a floating path that allows visitors to walk directly over the mudflats to see mudskippers, fiddler crabs, and various mangrove species up close without disturbing the delicate soil. For birdwatchers, the park is a premier destination, especially during the migratory season when thousands of birds stop over in the marshes and freshwater ponds; several three-story bird hides equipped with telescopes are strategically placed around the reserve, offering silent vantage points to observe rare species like the black-faced spoonbill. The landscape provides a striking visual contrast, where the tranquil, horizontal expanse of reeds and water is framed by the vertical forest of high-rise residential towers in Tin Shui Wai, serving as a constant reminder of the delicate balance between urban growth and environmental preservation. Throughout the year, the park hosts various educational workshops and guided tours that highlight the functions of wetlands in water purification and flood control, making it a critical hub for environmental research and community engagement. Whether exploring the Successive Exhibition Galleries or trekking through the Wildside Walk, visitors experience a side of Hong Kong that feels worlds away from the city's neon-lit streets, defined instead by the rhythmic sounds of cicadas and the sight of herons gliding over the water at dusk.
A93: ayld007 | B93: Tin Sau Bazaar | C93: =IF($A93<>"", _xlfn.IFNA(VLOOKUP(RIGHT(LEFT($A93,4),3),'District LookUp Table'!$A$2:$B$19,2,FALSE), "NOT FOUND"), "") -> Yuen Long | D93: 22.465715, 114.000768 | E93: Heritage & Culture | K93: If you're looking for a shopping experience that feels a world away from the shiny, cookie-cutter malls in the city center, you've got to check out Tin Sau Bazaar in Tin Shui Wai North, which is basically this open-air grid of about 130 tiny stalls run by the Tung Wah Group of Hospitals to help out the local grassroots community. I stumbled upon it while visiting the nearby Wetland Park, and it has such a raw, neighborhood vibe where you can find everything from super cheap household hardware and stationery to those random little hair salons and garment alteration shops that you don't see much of anymore. It's definitely not fancy—the shops are all housed in these uniform, prefabricated containers lined up in rows—but there's something really authentic about seeing the elderly residents from the surrounding public housing estates chatting with the stall owners, who are often locals themselves trying to make a living with the lower rents. You can pick up daily necessities like dried seafood, fresh eggs, or even some surprisingly good street snacks and halal food for way less than what you'd pay at a chain supermarket, though you have to be prepared for the weather since it's entirely outdoors. I went on a humid afternoon and it was pretty scorching even with the big sun umbrellas they've installed, but when a breeze kicks in or during the cooler months, it's actually a nice place to just wander and see the "real" side of life in the New Territories. It's got a bit of a "dawn market" legacy since it was built to give illegal street hawkers a permanent home, and while it's sometimes a bit quiet on weekdays, it really comes alive during their weekend arts fairs or community events. It might not be a tourist destination in the traditional sense, but if you value social enterprises and want to support a place that actually helps low-income families while finding some hidden gems for a few dollars, it's worth the short Light Rail trip to the Tin Sau stop.
A94: ayld008 | B94: Go Green Organic Farm | C94: =IF($A94<>"", _xlfn.IFNA(VLOOKUP(RIGHT(LEFT($A94,4),3),'District LookUp Table'!$A$2:$B$19,2,FALSE), "NOT FOUND"), "") -> Yuen Long | D94: 22.433645, 114.061176 | E94: Recreation & Activities | H94: Chill, Family Friendly
A95: ayld009 | C95: =IF($A95<>"", _xlfn.IFNA(VLOOKUP(RIGHT(LEFT($A95,4),3),'District LookUp Table'!$A$2:$B$19,2,FALSE), "NOT FOUND"), "") -> Yuen Long
A96: ayld010 | C96: =IF($A96<>"", _xlfn.IFNA(VLOOKUP(RIGHT(LEFT($A96,4),3),'District LookUp Table'!$A$2:$B$19,2,FALSE), "NOT FOUND"), "") -> Yuen Long
A97: aytm001 | C97: =IF($A97<>"", _xlfn.IFNA(VLOOKUP(RIGHT(LEFT($A97,4),3),'District LookUp Table'!$A$2:$B$19,2,FALSE), "NOT FOUND"), "") -> Yau Tsim Mong
A98: aytm002 | C98: =IF($A98<>"", _xlfn.IFNA(VLOOKUP(RIGHT(LEFT($A98,4),3),'District LookUp Table'!$A$2:$B$19,2,FALSE), "NOT FOUND"), "") -> Yau Tsim Mong
A99: aytm003 | C99: =IF($A99<>"", _xlfn.IFNA(VLOOKUP(RIGHT(LEFT($A99,4),3),'District LookUp Table'!$A$2:$B$19,2,FALSE), "NOT FOUND"), "") -> Yau Tsim Mong
A100: aytm004 | C100: =IF($A100<>"", _xlfn.IFNA(VLOOKUP(RIGHT(LEFT($A100,4),3),'District LookUp Table'!$A$2:$B$19,2,FALSE), "NOT FOUND"), "") -> Yau Tsim Mong
A101: aytm005 | C101: =IF($A101<>"", _xlfn.IFNA(VLOOKUP(RIGHT(LEFT($A101,4),3),'District LookUp Table'!$A$2:$B$19,2,FALSE), "NOT FOUND"), "") -> Yau Tsim Mong
C102: =IF($A102<>"", _xlfn.IFNA(VLOOKUP(RIGHT(LEFT($A102,4),3),'District LookUp Table'!$A$2:$B$19,2,FALSE), "NOT FOUND"), "")
C103: =IF($A103<>"", _xlfn.IFNA(VLOOKUP(RIGHT(LEFT($A103,4),3),'District LookUp Table'!$A$2:$B$19,2,FALSE), "NOT FOUND"), "")
C104: =IF($A104<>"", _xlfn.IFNA(VLOOKUP(RIGHT(LEFT($A104,4),3),'District LookUp Table'!$A$2:$B$19,2,FALSE), "NOT FOUND"), "")
C105: =IF($A105<>"", _xlfn.IFNA(VLOOKUP(RIGHT(LEFT($A105,4),3),'District LookUp Table'!$A$2:$B$19,2,FALSE), "NOT FOUND"), "")
C106: =IF($A106<>"", _xlfn.IFNA(VLOOKUP(RIGHT(LEFT($A106,4),3),'District LookUp Table'!$A$2:$B$19,2,FALSE), "NOT FOUND"), "")
...

Sheet Restaurants
A1: id | B1: name | C1: district | D1: coordinates | E1: type | F1: cuisine | G1: famous_dish | H1: price_level | I1: opening_time | J1: description | K1: transport
A2: ryld001 | B2: Wing Shun Restaurant | C2: =IF(A2<>"", _xlfn.IFNA(VLOOKUP(RIGHT(LEFT(A2,4),3),'District LookUp Table'!$A$2:$B$19,2,FALSE), "NOT FOUND"), "") -> Yuen Long | E2: Cha Chaan Teng | F2: Hong Kong | G2: Satay Beef Noodle | H2: 51-100 | I2: 0630-1730 | K2: MTR, Bus, Light Rail
A3: ryld002 | B3: LokWu Noodles | C3: =IF(A3<>"", _xlfn.IFNA(VLOOKUP(RIGHT(LEFT(A3,4),3),'District LookUp Table'!$A$2:$B$19,2,FALSE), "NOT FOUND"), "") -> Yuen Long | E3: Restaurant | F3: Chinese | G3: Knife Cut Noodles | H3: 51-100 | I3: 1200-2200 | K3: Bus, Light Rail
A4: ryld003 | B4: 劉興記生煎包專門店 | C4: =IF(A4<>"", _xlfn.IFNA(VLOOKUP(RIGHT(LEFT(A4,4),3),'District LookUp Table'!$A$2:$B$19,2,FALSE), "NOT FOUND"), "") -> Yuen Long | E4: Restaurant | F4: Chinese | G4: Shengjian Mantou (Pan Fried Bun) | H4: 51-100 | I4: 1130-2030 | K4: Bus, Light Rail
A5: rtmd001 | B5: 雲川 | C5: =IF(A5<>"", _xlfn.IFNA(VLOOKUP(RIGHT(LEFT(A5,4),3),'District LookUp Table'!$A$2:$B$19,2,FALSE), "NOT FOUND"), "") -> Tuen Mun | E5: Restaurant | F5: Chinese | G5: Rice Noodles | H5: 51-100 | I5: 1100-2230 | K5: Bus, Light Rail
A6: rtmd002 | B6: 很得輝 | C6: =IF(A6<>"", _xlfn.IFNA(VLOOKUP(RIGHT(LEFT(A6,4),3),'District LookUp Table'!$A$2:$B$19,2,FALSE), "NOT FOUND"), "") -> Tuen Mun | E6: Snacks | F6: Hong Kong | G6: Fried Chicken | H6: <50 | I6: 1230-0200 | K6: Bus, Light Rail
A7: rtmd003 | B7: 1986正宗越南料理 VIETNAMESE RESTAURANT | C7: =IF(A7<>"", _xlfn.IFNA(VLOOKUP(RIGHT(LEFT(A7,4),3),'District LookUp Table'!$A$2:$B$19,2,FALSE), "NOT FOUND"), "") -> Tuen Mun | E7: Restaurant | F7: Vietnamese | G7: Pho (Vietnamese Noodle) | H7: 50-100 | I7: 1100-2030 | K7: MTR, Bus, Light Rail
A8: rtwd | C8: =IF(A8<>"", _xlfn.IFNA(VLOOKUP(RIGHT(LEFT(A8,4),3),'District LookUp Table'!$A$2:$B$19,2,FALSE), "NOT FOUND"), "") -> Tsuen Wan
C9: =IF(A9<>"", _xlfn.IFNA(VLOOKUP(RIGHT(LEFT(A9,4),3),'District LookUp Table'!$A$2:$B$19,2,FALSE), "NOT FOUND"), "")
C10: =IF(A10<>"", _xlfn.IFNA(VLOOKUP(RIGHT(LEFT(A10,4),3),'District LookUp Table'!$A$2:$B$19,2,FALSE), "NOT FOUND"), "")
C11: =IF(A11<>"", _xlfn.IFNA(VLOOKUP(RIGHT(LEFT(A11,4),3),'District LookUp Table'!$A$2:$B$19,2,FALSE), "NOT FOUND"), "")
C12: =IF(A12<>"", _xlfn.IFNA(VLOOKUP(RIGHT(LEFT(A12,4),3),'District LookUp Table'!$A$2:$B$19,2,FALSE), "NOT FOUND"), "")
C13: =IF(A13<>"", _xlfn.IFNA(VLOOKUP(RIGHT(LEFT(A13,4),3),'District LookUp Table'!$A$2:$B$19,2,FALSE), "NOT FOUND"), "")
C14: =IF(A14<>"", _xlfn.IFNA(VLOOKUP(RIGHT(LEFT(A14,4),3),'District LookUp Table'!$A$2:$B$19,2,FALSE), "NOT FOUND"), "")
C15: =IF(A15<>"", _xlfn.IFNA(VLOOKUP(RIGHT(LEFT(A15,4),3),'District LookUp Table'!$A$2:$B$19,2,FALSE), "NOT FOUND"), "")
C16: =IF(A16<>"", _xlfn.IFNA(VLOOKUP(RIGHT(LEFT(A16,4),3),'District LookUp Table'!$A$2:$B$19,2,FALSE), "NOT FOUND"), "")
C17: =IF(A17<>"", _xlfn.IFNA(VLOOKUP(RIGHT(LEFT(A17,4),3),'District LookUp Table'!$A$2:$B$19,2,FALSE), "NOT FOUND"), "")
C18: =IF(A18<>"", _xlfn.IFNA(VLOOKUP(RIGHT(LEFT(A18,4),3),'District LookUp Table'!$A$2:$B$19,2,FALSE), "NOT FOUND"), "")
C19: =IF(A19<>"", _xlfn.IFNA(VLOOKUP(RIGHT(LEFT(A19,4),3),'District LookUp Table'!$A$2:$B$19,2,FALSE), "NOT FOUND"), "")
C20: =IF(A20<>"", _xlfn.IFNA(VLOOKUP(RIGHT(LEFT(A20,4),3),'District LookUp Table'!$A$2:$B$19,2,FALSE), "NOT FOUND"), "")
... C50: =IF(A50<>"", _xlfn.IFNA(VLOOKUP(RIGHT(LEFT(A50,4),3),'District LookUp Table'!$A$2:$B$19,2,FALSE), "NOT FOUND"), "")

Sheet District LookUp Table
A1: id | B1: district
A2: cwd | B2: Central & Western
A3: ead | B3: Eastern
A4: isd | B4: Islands
A5: kcd | B5: Kowloon City
A6: ktd | B6: Kwun Tong
A7: kwd | B7: Kwai Tsing
A8: nod | B8: North
A9: skd | B9: Sai Kung
A10: std | B10: Sha Tin
A11: ssp | B11: Sham Shui Po
A12: sod | B12: Southern
... A19: yld | B19: Yuen Long

Sheet Tags
A1: Categories | B1: Vibe | C1: Environmental Tags | D1: Demographic Tags | E1: Budget
A2: Nature & Scenary | B2: Chill | C2: Outdoor | D2: Tourist Friendly | E2: Free
A3: Heritage & Culture | B3: Romantic | C3: Indoor | D3: Family Friendly | E3: <100
A4: Food & Drink | B4: Bustling | C4: Budget | D4: Couples | E4: 100-500
A5: Recreation & Activities | B5: Zen | C5: Free | D5: Solo Travelers | E5: >500
A6: Urban & Architecture | B6: Insta-Worthy | C6: Steep Terrain | D6: Elderly Friendly
A7: Shopping | B7: Retro/Nostalgic | C7: Urban | D7: Pet Friendly
A8: Religious & Spiritual | B8: Industrial
B9: Hidden
B10: Local Favorites
